{
 "custom_fields": [
  {
   "_assign": null,
   "_comments": null,
   "_liked_by": null,
   "_user_tags": null,
   "allow_on_submit": 0,
   "bold": 0,
   "collapsible": 0,
   "collapsible_depends_on": null,
   "columns": 0,
   "creation": "2019-11-02 13:30:24.563990",
   "default": null,
   "depends_on": null,
   "description": null,
   "docstatus": 0,
   "dt": "Lead",
   "fetch_from": null,
   "fetch_if_empty": 0,
   "fieldname": "services",
   "fieldtype": "Data",
   "hidden": 0,
   "idx": 7,
   "ignore_user_permissions": 0,
   "ignore_xss_filter": 0,
   "in_global_search": 0,
   "in_list_view": 0,
   "in_standard_filter": 0,
   "insert_after": "email_id",
   "label": "Services",
   "modified": "2019-11-02 13:30:24.563990",
   "modified_by": "Administrator",
   "name": "Lead-services",
   "no_copy": 0,
   "options": null,
   "owner": "Administrator",
   "parent": null,
   "parentfield": null,
   "parenttype": null,
   "permlevel": 0,
   "precision": "",
   "print_hide": 0,
   "print_hide_if_no_value": 0,
   "print_width": null,
   "read_only": 1,
   "report_hide": 0,
   "reqd": 0,
   "search_index": 0,
   "translatable": 1,
   "unique": 0,
   "width": null
  },
  {
   "_assign": null,
   "_comments": null,
   "_liked_by": null,
   "_user_tags": null,
   "allow_on_submit": 0,
   "bold": 0,
   "collapsible": 0,
   "collapsible_depends_on": null,
   "columns": 0,
   "creation": "2019-11-02 13:31:04.351965",
   "default": null,
   "depends_on": null,
   "description": null,
   "docstatus": 0,
   "dt": "Lead",
   "fetch_from": null,
   "fetch_if_empty": 0,
   "fieldname": "captcha_code",
   "fieldtype": "Data",
   "hidden": 1,
   "idx": 14,
   "ignore_user_permissions": 0,
   "ignore_xss_filter": 0,
   "in_global_search": 0,
   "in_list_view": 0,
   "in_standard_filter": 0,
   "insert_after": "source",
   "label": "Captcha Code",
   "modified": "2019-11-02 13:31:04.351965",
   "modified_by": "Administrator",
   "name": "Lead-captcha_code",
   "no_copy": 0,
   "options": null,
   "owner": "Administrator",
   "parent": null,
   "parentfield": null,
   "parenttype": null,
   "permlevel": 0,
   "precision": "",
   "print_hide": 0,
   "print_hide_if_no_value": 0,
   "print_width": null,
   "read_only": 0,
   "report_hide": 0,
   "reqd": 0,
   "search_index": 0,
   "translatable": 1,
   "unique": 0,
   "width": null
  },
  {
   "_assign": null,
   "_comments": null,
   "_liked_by": null,
   "_user_tags": null,
   "allow_on_submit": 0,
   "bold": 0,
   "collapsible": 0,
   "collapsible_depends_on": null,
   "columns": 0,
   "creation": "2019-11-02 13:32:18.301785",
   "default": null,
   "depends_on": null,
   "description": null,
   "docstatus": 0,
   "dt": "Lead",
   "fetch_from": null,
   "fetch_if_empty": 0,
   "fieldname": "message",
   "fieldtype": "Small Text",
   "hidden": 0,
   "idx": 8,
   "ignore_user_permissions": 0,
   "ignore_xss_filter": 0,
   "in_global_search": 0,
   "in_list_view": 0,
   "in_standard_filter": 0,
   "insert_after": "services",
   "label": "Message",
   "modified": "2019-11-02 13:32:18.301785",
   "modified_by": "Administrator",
   "name": "Lead-message",
   "no_copy": 0,
   "options": null,
   "owner": "Administrator",
   "parent": null,
   "parentfield": null,
   "parenttype": null,
   "permlevel": 0,
   "precision": "",
   "print_hide": 0,
   "print_hide_if_no_value": 0,
   "print_width": null,
   "read_only": 0,
   "report_hide": 0,
   "reqd": 0,
   "search_index": 0,
   "translatable": 1,
   "unique": 0,
   "width": null
  }
 ],
 "custom_perms": [],
 "doctype": "Lead",
 "property_setters": [],
 "sync_on_migrate": 1
}